{
	"animations": [
		{
			"loop": false,
			"offsets": [
				0,
				0
			],
			"anim": "deathLoop",
			"fps": 12,
			"name": "ded_loop",
			"indices": []
		},
		{
			"loop": false,
			"offsets": [
				0,
				0
			],
			"anim": "deathConfirm",
			"fps": 12,
			"name": "ded_restart",
			"indices": []
		},
		{
			"offsets": [
				0,
				0
			],
			"loop": false,
			"fps": 12,
			"anim": "firstDeath",
			"indices": [],
			"name": "ded_start"
		}
	],
	"no_antialiasing": false,
	"image": "characters/nastya-dead",
	"position": [
		-320,
		-615
	],
	"health_bar": "default",
	"healthicon": "Pnastya",
	"flip_x": false,
	"healthbar_colors": [
		255,
		175,
		175
	],
	"camera_position": [
		80,
		-40
	],
	"sing_duration": 8.1,
	"scale": 0.75
}