{
	"animations": [
		{
			"loop": false,
			"offsets": [
				-5,
				0
			],
			"anim": "idle",
			"fps": 24,
			"name": "idle",
			"indices": []
		},
		{
			"offsets": [
				274,
				89
			],
			"loop": false,
			"fps": 24,
			"anim": "singLEFT",
			"indices": [],
			"name": "left"
		},
		{
			"offsets": [
				227,
				-16
			],
			"loop": false,
			"fps": 24,
			"anim": "singDOWN",
			"indices": [],
			"name": "down"
		},
		{
			"offsets": [
				23,
				84
			],
			"loop": false,
			"fps": 24,
			"anim": "singUP",
			"indices": [],
			"name": "up"
		},
		{
			"offsets": [
				-10,
				34
			],
			"loop": false,
			"fps": 24,
			"anim": "singRIGHT",
			"indices": [],
			"name": "right"
		},
		{
			"loop": false,
			"offsets": [
				224,
				-15
			],
			"anim": "singLEFTmiss",
			"fps": 24,
			"name": "missL",
			"indices": []
		},
		{
			"loop": false,
			"offsets": [
				122,
				-79
			],
			"anim": "singDOWNmiss",
			"fps": 24,
			"name": "missD",
			"indices": []
		},
		{
			"loop": false,
			"offsets": [
				23,
				123
			],
			"anim": "singUPmiss",
			"fps": 24,
			"name": "missU",
			"indices": []
		},
		{
			"loop": false,
			"offsets": [
				-10,
				10
			],
			"anim": "singRIGHTmiss",
			"fps": 24,
			"name": "missR",
			"indices": []
		}
	],
	"no_antialiasing": false,
	"image": "characters/wizardNastya",
	"position": [
		90,
		280
	],
	"health_bar": "nastya",
	"healthicon": "nastyaSG",
	"flip_x": true,
	"healthbar_colors": [
		195,
		0,
		81
	],
	"camera_position": [
		250,
		-110
	],
	"sing_duration": 4,
	"scale": 1.1
}